prompt_verse/__init__.py
prompt_verse/generate_report.py
prompt_verse/gradio_ui.py
prompt_verse/prompt_core_executor.py
prompt_verse/prompt_lib/chat_summary_prompt.py
prompt_verse/prompt_lib/context_question_answering_prompt.py
prompt_verse/prompt_lib/few_shot_prompt.py
prompt_verse/prompt_lib/language_detection_prompt.py
prompt_verse/prompt_lib/prompt_lib_description.csv
prompt_verse/prompt_lib/sentiment_analysis_prompt.py
prompt_verse/prompt_lib/summarization_prompt.py
prompt_verse/prompt_lib/topic_classification_prompt.py
prompt_verse/prompt_lib/translation_prompt.py
prompt_verse/prompt_lib/zero_shot_prompt.py
prompt_verse/prompt_maintenance.py
prompt_verse/prompt_verse.py
prompt_verse/session.py
prompt_verse/session_maintenance.py
prompt_verse/validations.py
prompt_verse-1.0.1.dist-info/LICENSE
prompt_verse-1.0.1.dist-info/METADATA
prompt_verse-1.0.1.dist-info/WHEEL
prompt_verse-1.0.1.dist-info/RECORD
