Metadata-Version: 2.1
Name: prompt-verse
Version: 1.0.1
Summary: The PromptVerse package is designed to enhance the capabilities of developers in writing prompts, logging them, and providing a prompt registry.
Author: Krishna Chaitanya Gollapudi
Author-email: krsna.sri1@gmail.com
Requires-Python: >=3.11,<4.0
Classifier: Programming Language :: Python :: 3
Classifier: Programming Language :: Python :: 3.11
Requires-Dist: aiofiles (==22.1.0)
Requires-Dist: aiohttp (==3.8.4)
Requires-Dist: altair (==5.0.1)
Requires-Dist: better-profanity (==0.7.0)
Requires-Dist: black (==22.3.0)
Requires-Dist: certifi (==2023.5.7)
Requires-Dist: clyent (==1.2.1)
Requires-Dist: dataclasses-json (==0.5.9)
Requires-Dist: docutils (==0.14)
Requires-Dist: ffmpy (==0.3.0)
Requires-Dist: fonttools (==4.40.0)
Requires-Dist: frozenlist (==1.3.3)
Requires-Dist: fsspec (==2023.6.0)
Requires-Dist: gradio (==3.36.1)
Requires-Dist: gradio-client (==0.2.8)
Requires-Dist: httpcore (==0.16.3)
Requires-Dist: httpx (==0.23.3)
Requires-Dist: huggingface-hub (==0.16.4)
Requires-Dist: joblib (>=1.3.1,<2.0.0)
Requires-Dist: jsonschema (==4.18.1)
Requires-Dist: jsonschema-specifications (==2023.6.1)
Requires-Dist: keyring (==23.9.0)
Requires-Dist: langchain (==0.0.230)
Requires-Dist: marshmallow (==3.19.0)
Requires-Dist: nbformat (==5.4.0)
Requires-Dist: numpy (==1.24)
Requires-Dist: openai (==0.27.8)
Requires-Dist: pandas (==2.0.3)
Requires-Dist: pyyaml (==6.0)
Requires-Dist: referencing (==0.29.1)
Requires-Dist: requests (==2.28.1)
Requires-Dist: rpds-py (==0.8.10)
Requires-Dist: sqlalchemy (==2.0.18)
Requires-Dist: tiktoken (==0.4.0)
Requires-Dist: urllib3 (==1.26.0)
Requires-Dist: uvicorn (==0.22.0)
Requires-Dist: websockets (==10.4)
Requires-Dist: zipp (==3.16.0)
